lyrics/__init__.py
lyrics/server.py
lyrics/bash/command_parser.py
lyrics/bash/environment.py
lyrics/bash/executor.py
lyrics/bash/session_manager.py
lyrics/bash/types.py
lyrics/client/__init__.py
lyrics/client/bash_client.py
lyrics/commands/python_handler.py
lyrics/commands/read_handler.py
lyrics/commands/system_handler.py
lyrics/filesystem/resolver.py
lyrics/filesystem/validator.py
ailyrics-0.1.0.dist-info/METADATA
ailyrics-0.1.0.dist-info/WHEEL
ailyrics-0.1.0.dist-info/licenses/LICENSE
ailyrics-0.1.0.dist-info/RECORD
