Metadata-Version: 2.4
Name: ailyrics
Version: 0.1.0
Summary: Super connection middleware about multi-agent and skills
Author-email: fangyinc <staneyffer@gmail.com>
License-Expression: MIT
License-File: LICENSE
Requires-Python: >=3.10
Requires-Dist: fastapi>=0.104.0
Requires-Dist: httpx>=0.25.0
Requires-Dist: pexpect>=4.9.0
Requires-Dist: pydantic>=2.4.0
Requires-Dist: python-multipart>=0.0.6
Requires-Dist: pyyaml>=6.0
Requires-Dist: uvicorn[standard]>=0.24.0
